<?xml version='1.0'?>
<ns2:test-suite xmlns:ns2='urn:model.allure.qatools.yandex.ru' start='1537417256097' stop='1537417269382'>
    <name>Home:</name>
    <title>Home:</title>
    <test-cases>
        <test-case start='1537417256101' status='passed' stop='1537417269325'>
            <name>test something</name>
            <title>test something</title>
            <labels/>
            <parameters/>
            <steps>
                <step start='1537417259727' status='passed' stop='1537417262685'>
                    <name>I am on page "/"</name>
                    <title>I am on page "/"</title>
                    <attachments/>
                    <steps/>
                </step>
                <step start='1537417262685' status='passed' stop='1537417262771'>
                    <name>I see "CURA Healthcare Service"</name>
                    <title>I see "CURA Healthcare Service"</title>
                    <attachments/>
                    <steps/>
                </step>
                <step start='1537417262771' status='passed' stop='1537417263355'>
                    <name>I click "#btn-make-appointment"</name>
                    <title>I click "#btn-make-appointment"</title>
                    <attachments/>
                    <steps/>
                </step>
                <step start='1537417263355' status='passed' stop='1537417263416'>
                    <name>I see "Login"</name>
                    <title>I see "Login"</title>
                    <attachments/>
                    <steps/>
                </step>
                <step start='1537417263416' status='passed' stop='1537417263423'>
                    <name>I see current url equals "/profile.php#login"</name>
                    <title>I see current url equals "/profile.php#login"</title>
                    <attachments/>
                    <steps/>
                </step>
                <step start='1537417263423' status='passed' stop='1537417263535'>
                    <name>I fill field "#txt-username", "John Doe"</name>
                    <title>I fill field "#txt-username", "John Doe"</title>
                    <attachments/>
                    <steps/>
                </step>
                <step start='1537417263535' status='passed' stop='1537417263675'>
                    <name>I fill field "#txt-password", "ThisIsNotAPassword"</name>
                    <title>I fill field "#txt-password", "ThisIsNotAPassword"</title>
                    <attachments/>
                    <steps/>
                </step>
                <step start='1537417263675' status='passed' stop='1537417264426'>
                    <name>I click "#btn-login"</name>
                    <title>I click "#btn-login"</title>
                    <attachments/>
                    <steps/>
                </step>
                <step start='1537417264426' status='passed' stop='1537417265428'>
                    <name>I wait 1</name>
                    <title>I wait 1</title>
                    <attachments/>
                    <steps/>
                </step>
                <step start='1537417265428' status='passed' stop='1537417265562'>
                    <name>I dont see "Login failed! Please ensure the username and password are valid."</name>
                    <title>I dont see "Login failed! Please ensure the username and password are valid."</title>
                    <attachments/>
                    <steps/>
                </step>
                <step start='1537417265562' status='passed' stop='1537417265606'>
                    <name>I see "Make Appointment"</name>
                    <title>I see "Make Appointment"</title>
                    <attachments/>
                    <steps/>
                </step>
                <step start='1537417265606' status='passed' stop='1537417265668'>
                    <name>I select option "#combo_facility", "Hongkong CURA Healthcare Center"</name>
                    <title>I select option "#combo_facility", "Hongkong CURA Healthcare Center"</title>
                    <attachments/>
                    <steps/>
                </step>
                <step start='1537417265668' status='passed' stop='1537417265754'>
                    <name>I check option "#chk_hospotal_readmission"</name>
                    <title>I check option "#chk_hospotal_readmission"</title>
                    <attachments/>
                    <steps/>
                </step>
                <step start='1537417265754' status='passed' stop='1537417265819'>
                    <name>I click "#radio_program_none"</name>
                    <title>I click "#radio_program_none"</title>
                    <attachments/>
                    <steps/>
                </step>
                <step start='1537417265819' status='passed' stop='1537417265907'>
                    <name>I click "#txt_visit_date"</name>
                    <title>I click "#txt_visit_date"</title>
                    <attachments/>
                    <steps/>
                </step>
                <step start='1537417265907' status='passed' stop='1537417265974'>
                    <name>I click ".datepicker-switch"</name>
                    <title>I click ".datepicker-switch"</title>
                    <attachments/>
                    <steps/>
                </step>
                <step start='1537417265975' status='passed' stop='1537417266061'>
                    <name>I click {xpath: .//*[contains(concat(' ', normalize-space(./@class), ' '), ' table-condensed ')]//td//*[contains(concat(' ', normalize-space(./@class), ' '), ' month ')][contains(., 'Oct')]}</name>
                    <title>I click {xpath: .//*[contains(concat(' ', normalize-space(./@class), ' '), ' table-condensed ')]//td//*[contains(concat(' ', normalize-space(./@class), ' '), ' month ')][contains(., 'Oct')]}</title>
                    <attachments/>
                    <steps/>
                </step>
                <step start='1537417266061' status='passed' stop='1537417266137'>
                    <name>I click {xpath: .//*[contains(concat(' ', normalize-space(./@class), ' '), ' table-condensed ')]//td[position()=4]}</name>
                    <title>I click {xpath: .//*[contains(concat(' ', normalize-space(./@class), ' '), ' table-condensed ')]//td[position()=4]}</title>
                    <attachments/>
                    <steps/>
                </step>
                <step start='1537417266137' status='passed' stop='1537417266200'>
                    <name>I click "#txt_comment"</name>
                    <title>I click "#txt_comment"</title>
                    <attachments/>
                    <steps/>
                </step>
                <step start='1537417266200' status='passed' stop='1537417266308'>
                    <name>I fill field "#txt_comment", "I will see you"</name>
                    <title>I fill field "#txt_comment", "I will see you"</title>
                    <attachments/>
                    <steps/>
                </step>
                <step start='1537417266308' status='passed' stop='1537417266718'>
                    <name>I click "#btn-book-appointment"</name>
                    <title>I click "#btn-book-appointment"</title>
                    <attachments/>
                    <steps/>
                </step>
                <step start='1537417266718' status='passed' stop='1537417266816'>
                    <name>I see "Appointment Confirmation"</name>
                    <title>I see "Appointment Confirmation"</title>
                    <attachments/>
                    <steps/>
                </step>
                <step start='1537417266816' status='passed' stop='1537417267254'>
                    <name>I click ".btn.btn-default"</name>
                    <title>I click ".btn.btn-default"</title>
                    <attachments/>
                    <steps/>
                </step>
                <step start='1537417267254' status='passed' stop='1537417267345'>
                    <name>I see "Make Appointment"</name>
                    <title>I see "Make Appointment"</title>
                    <attachments/>
                    <steps/>
                </step>
                <step start='1537417267345' status='passed' stop='1537417267403'>
                    <name>I click "#menu-toggle"</name>
                    <title>I click "#menu-toggle"</title>
                    <attachments/>
                    <steps/>
                </step>
                <step start='1537417267403' status='passed' stop='1537417267860'>
                    <name>I click {xpath: .//*[contains(concat(' ', normalize-space(./@class), ' '), ' sidebar-nav ')]//a[contains(., 'History')]}</name>
                    <title>I click {xpath: .//*[contains(concat(' ', normalize-space(./@class), ' '), ' sidebar-nav ')]//a[contains(., 'History')]}</title>
                    <attachments/>
                    <steps/>
                </step>
                <step start='1537417267860' status='passed' stop='1537417267953'>
                    <name>I see "History"</name>
                    <title>I see "History"</title>
                    <attachments/>
                    <steps/>
                </step>
                <step start='1537417267954' status='passed' stop='1537417268041'>
                    <name>I click "#menu-toggle"</name>
                    <title>I click "#menu-toggle"</title>
                    <attachments/>
                    <steps/>
                </step>
                <step start='1537417268041' status='passed' stop='1537417268460'>
                    <name>I click {xpath: .//*[contains(concat(' ', normalize-space(./@class), ' '), ' sidebar-nav ')]//a[contains(., 'Profil')]}</name>
                    <title>I click {xpath: .//*[contains(concat(' ', normalize-space(./@class), ' '), ' sidebar-nav ')]//a[contains(., 'Profil')]}</title>
                    <attachments/>
                    <steps/>
                </step>
                <step start='1537417268460' status='passed' stop='1537417268573'>
                    <name>I see "Profil"</name>
                    <title>I see "Profil"</title>
                    <attachments/>
                    <steps/>
                </step>
                <step start='1537417268573' status='passed' stop='1537417269287'>
                    <name>I click ".btn.btn-default"</name>
                    <title>I click ".btn.btn-default"</title>
                    <attachments/>
                    <steps/>
                </step>
                <step start='1537417269287' status='passed' stop='1537417269325'>
                    <name>I see "CURA Healthcare Service"</name>
                    <title>I see "CURA Healthcare Service"</title>
                    <attachments/>
                    <steps/>
                </step>
            </steps>
            <attachments/>
        </test-case>
    </test-cases>
</ns2:test-suite>